plimver/__init__.py
plimver-1.0.0.dist-info/METADATA
plimver-1.0.0.dist-info/WHEEL
plimver-1.0.0.dist-info/RECORD
