Metadata-Version: 2.4
Name: plimver
Version: 1.0.0
Summary: Official Python SDK for Plimver AI Platform - Unified LLM, RAG, and Memory API
Project-URL: Homepage, https://plimvr.tech
Project-URL: Documentation, https://plimvr.tech/docs/sdk
Project-URL: Repository, https://github.com/Elliot-Elikplim/Plimver-AI-Infra
Project-URL: Issues, https://github.com/Elliot-Elikplim/Plimver-AI-Infra/issues
Author-email: Plimver Team <team@plimvr.tech>
License-Expression: MIT
Keywords: ai,anthropic,chatbot,gemini,llm,memory,openai,plimver,rag,sdk,vector-search
Classifier: Development Status :: 5 - Production/Stable
Classifier: Intended Audience :: Developers
Classifier: License :: OSI Approved :: MIT License
Classifier: Operating System :: OS Independent
Classifier: Programming Language :: Python :: 3
Classifier: Programming Language :: Python :: 3.8
Classifier: Programming Language :: Python :: 3.9
Classifier: Programming Language :: Python :: 3.10
Classifier: Programming Language :: Python :: 3.11
Classifier: Programming Language :: Python :: 3.12
Classifier: Topic :: Scientific/Engineering :: Artificial Intelligence
Classifier: Typing :: Typed
Requires-Python: >=3.8
Requires-Dist: httpx>=0.24.0
Provides-Extra: dev
Requires-Dist: mypy>=1.0.0; extra == 'dev'
Requires-Dist: pytest-asyncio>=0.21.0; extra == 'dev'
Requires-Dist: pytest-cov>=4.0.0; extra == 'dev'
Requires-Dist: pytest>=7.0.0; extra == 'dev'
Requires-Dist: ruff>=0.1.0; extra == 'dev'
